[
    {
        "module": "LCD_i2c_GSOE/LCD.o",
        "size": {
            ".text": 612,
            ".data": 0,
            ".bss": 0,
            ".text-delta": 0,
            ".data-delta": 0,
            ".bss-delta": 0
        }
    },
    {
        "module": "LCD_i2c_GSOE/SoftwareI2C.o",
        "size": {
            ".text": 896,
            ".data": 0,
            ".bss": 0,
            ".text-delta": 0,
            ".data-delta": 0,
            ".bss-delta": 0
        }
    },
    {
        "module": "[lib]/c_w.l",
        "size": {
            ".text": 4202,
            ".data": 16,
            ".bss": 348,
            ".text-delta": 0,
            ".data-delta": 0,
            ".bss-delta": 0
        }
    },
    {
        "module": "[lib]/libcppabi_w.l",
        "size": {
            ".text": 44,
            ".data": 0,
            ".bss": 0,
            ".text-delta": 0,
            ".data-delta": 0,
            ".bss-delta": 0
        }
    },
    {
        "module": "anon$$obj.o",
        "size": {
            ".text": 32,
            ".data": 0,
            ".bss": 1024,
            ".text-delta": 0,
            ".data-delta": 0,
            ".bss-delta": 0
        }
    },
    {
        "module": "main.o",
        "size": {
            ".text": 340,
            ".data": 0,
            ".bss": 12,
            ".text-delta": 0,
            ".data-delta": 0,
            ".bss-delta": 0
        }
    },
    {
        "module": "mbed-os/cmsis",
        "size": {
            ".text": 9634,
            ".data": 168,
            ".bss": 7122,
            ".text-delta": 0,
            ".data-delta": 0,
            ".bss-delta": 0
        }
    },
    {
        "module": "mbed-os/connectivity",
        "size": {
            ".text": 228,
            ".data": 0,
            ".bss": 0,
            ".text-delta": 0,
            ".data-delta": 0,
            ".bss-delta": 0
        }
    },
    {
        "module": "mbed-os/drivers",
        "size": {
            ".text": 294,
            ".data": 0,
            ".bss": 0,
            ".text-delta": 0,
            ".data-delta": 0,
            ".bss-delta": 0
        }
    },
    {
        "module": "mbed-os/hal",
        "size": {
            ".text": 1488,
            ".data": 4,
            ".bss": 58,
            ".text-delta": 0,
            ".data-delta": 0,
            ".bss-delta": 0
        }
    },
    {
        "module": "mbed-os/platform",
        "size": {
            ".text": 7649,
            ".data": 64,
            ".bss": 340,
            ".text-delta": 0,
            ".data-delta": 0,
            ".bss-delta": 0
        }
    },
    {
        "module": "mbed-os/rtos",
        "size": {
            ".text": 438,
            ".data": 0,
            ".bss": 0,
            ".text-delta": 0,
            ".data-delta": 0,
            ".bss-delta": 0
        }
    },
    {
        "module": "mbed-os/targets",
        "size": {
            ".text": 7197,
            ".data": 8,
            ".bss": 478,
            ".text-delta": 0,
            ".data-delta": 0,
            ".bss-delta": 0
        }
    },
    {
        "summary": {
            "static_ram": 9642,
            "static_ram_delta": 0,
            "total_flash": 33314,
            "total_flash_delta": 0
        }
    }
]
